django_pyref-0.6.6.dist-info/licenses/LICENSE
refs/__init__.py
refs/admin.py
refs/api_views.py
refs/apps.py
refs/export_utils.py
refs/filters.py
refs/forms.py
refs/models.py
refs/serializers.py
refs/urls.py
refs/utils.py
refs/views.py
refs/xsams_generators.py
refs/xsams_settings.py
refs/xsams_utils.py
refs/migrations/0001_initial.py
refs/migrations/__init__.py
refs/templates/refs/base.html
refs/templates/refs/edit.html
refs/templates/refs/pagination.html
refs/templates/refs/refs-list.html
refs/templates/refs/search.html
refs/templatetags/__init__.py
refs/templatetags/pyref_tags.py
django_pyref-0.6.6.dist-info/METADATA
django_pyref-0.6.6.dist-info/WHEEL
django_pyref-0.6.6.dist-info/top_level.txt
django_pyref-0.6.6.dist-info/RECORD
